raptorfinance/__init__.py
raptorfinance-0.0.1.dist-info/LICENSE
raptorfinance-0.0.1.dist-info/METADATA
raptorfinance-0.0.1.dist-info/WHEEL
raptorfinance-0.0.1.dist-info/top_level.txt
raptorfinance-0.0.1.dist-info/RECORD
