Metadata-Version: 2.1
Name: raptorfinance
Version: 0.0.1
Summary: finance api especially for Indian NSE/BSE Stock Data
Home-page: https://github.com/swaroop9ai9/raptorfinance
Author: M V D SATYA SWAROOP
Author-email: swaroop9ai9@gmail.com
License: UNKNOWN
Platform: UNKNOWN
Classifier: Programming Language :: Python :: 3
Classifier: License :: OSI Approved :: MIT License
Classifier: Operating System :: OS Independent
Requires-Dist: pandas
Requires-Dist: requests
